wfbase.py
wfbase-0.0.2.dist-info/LICENSE
wfbase-0.0.2.dist-info/METADATA
wfbase-0.0.2.dist-info/WHEEL
wfbase-0.0.2.dist-info/top_level.txt
wfbase-0.0.2.dist-info/RECORD
